eco4weather/__init__.py
eco4weather/hoel.py
eco4weather/ramsey.py
eco4weather/socialplanner.py
eco4weather-1.0.1.dist-info/LICENCE.txt
eco4weather-1.0.1.dist-info/METADATA
eco4weather-1.0.1.dist-info/WHEEL
eco4weather-1.0.1.dist-info/top_level.txt
eco4weather-1.0.1.dist-info/RECORD
