Metadata-Version: 2.1
Name: eco4weather
Version: 1.0.1
Summary: Econometrics for Weather and Climate Applications & Education
Home-page: https://github.com/opannekoucke/eco4weather
Author: Olivier Pannekoucke 
Author-email: olivier.pannekoucke@meteo.fr
Project-URL: Bug Tracker, https://github.com/opannekoucke/eco4weather/issues
Classifier: Programming Language :: Python :: 3
Classifier: License :: CeCILL-B Free Software License Agreement (CECILL-B) 
Classifier: Operating System :: OS Independent
Requires-Python: >=3.6
License-File: LICENCE.txt
